private_concept/__init__.py
private_concept/main.py
private_concept/prompts.py
private_concept-2025.12.21082713.dist-info/METADATA
private_concept-2025.12.21082713.dist-info/WHEEL
private_concept-2025.12.21082713.dist-info/top_level.txt
private_concept-2025.12.21082713.dist-info/RECORD
